turta_rcdriverhat/Turta_IMU.py
turta_rcdriverhat/Turta_RCDriver.py
turta_rcdriverhat/__init__.py
turta_rcdriverhat-1.0.0.dist-info/LICENCE
turta_rcdriverhat-1.0.0.dist-info/METADATA
turta_rcdriverhat-1.0.0.dist-info/WHEEL
turta_rcdriverhat-1.0.0.dist-info/top_level.txt
turta_rcdriverhat-1.0.0.dist-info/RECORD
